yourlinearregressionlibrary/__init__.py
yourlinearregressionlibrary/yourlinearregressionlibrary.py
yourlinearregressionlibrary-1.0.0.dist-info/LICENCE.txt
yourlinearregressionlibrary-1.0.0.dist-info/METADATA
yourlinearregressionlibrary-1.0.0.dist-info/WHEEL
yourlinearregressionlibrary-1.0.0.dist-info/top_level.txt
yourlinearregressionlibrary-1.0.0.dist-info/RECORD
